setup.cfg
setup.py
bin/fetchsubs.py
pyopensubtitles/__init__.py
pyopensubtitles/pyopensubtitles.py
pyopensubtitles/settings.py
pyopensubtitles.egg-info/PKG-INFO
pyopensubtitles.egg-info/SOURCES.txt
pyopensubtitles.egg-info/dependency_links.txt
pyopensubtitles.egg-info/top_level.txt