Metadata-Version: 1.1
Name: pyopensubtitles
Version: 0.1
Summary: Python wrapper for OpenSubtitles API and a CLI tool to download subtitles
Home-page: https://github.com/rkrp/pyopensubtitles
Author: Krishna Ram Prakash R
Author-email: krp@gtux.in
License: GPLv3
Download-URL: https://github.com/rkrp/pyopensubtitles
Platform: UNKNOWN
Classifier: Development Status :: 4 - Beta
Classifier: Topic :: Utilities
